{
  "width": 70,
  "height": 25,
  "x": 0,
  "y": 0,
  "game_stats": {
    "width": 70,
    "height": 5,
    "x": 1,
    "y": 21,
    "fields": [
      {
        "field_name": "elapsed time: ",
        "x": 1,
        "y": 3,
        "field_width": 5
      },
      {
        "field_name": "bullets quantity: ",
        "x": 1,
        "y": 1,
        "field_width": 5
      },
      {
        "field_name": "lives: ",
        "x": 25,
        "y": 1,
        "field_width": 3
      }
    ]
  },
  "game_map": {
    "width": 70,
    "height": 20,
    "x": 0,
    "y": 0
  }
}
